spiralmoments/__init__.py
spiralmoments/height.py
spiralmoments/lindblad.py
spiralmoments/phi.py
spiralmoments/rotations.py
spiralmoments/spirals.py
spiralmoments/vfield.py
wakeflow/__init__.py
wakeflow/burgers.py
wakeflow/grid.py
wakeflow/linear_perts.py
wakeflow/mcfost_interface.py
wakeflow/model_setup.py
wakeflow/non_linear_perts.py
wakeflow/transformations.py
wakeflow/utilities.py
wakeflow/wakefit_interface.py
wakeflow/wakeflow.py
wakeflow/data/default_config.yaml
wakeflow/data/linear_perturbations.npy.tar.gz
wakeflow/data/linear_perturbations_mesh.npy.tar.gz
wakeflow/data/ref3.0_3D.para
wakeflow-1.4.0.dist-info/LICENSE
wakeflow-1.4.0.dist-info/METADATA
wakeflow-1.4.0.dist-info/WHEEL
wakeflow-1.4.0.dist-info/top_level.txt
wakeflow-1.4.0.dist-info/RECORD
