Metadata-Version: 2.1
Name: wakeflow
Version: 1.4.0
Summary: Generate and manipulate semi-analytic models of planet wakes
Home-page: https://github.com/TomHilder/wakeflow
Author: Thomas Hilder
Author-email: Thomas Hilder <tom.hilder.dlhp@gmail.com>
License: MIT License
Project-URL: Homepage, https://github.com/TomHilder/wakeflow
Keywords: astronomy,astrophysics,research,protoplanets,analytic,modelling,planet wake,protoplanetary,discs,disks
Platform: unix
Platform: linux
Platform: osx
Platform: windows
Classifier: License :: OSI Approved :: MIT License
Classifier: Programming Language :: Python
Classifier: Programming Language :: Python :: 3
Classifier: Topic :: Scientific/Engineering :: Astronomy
Classifier: Topic :: Scientific/Engineering :: Mathematics
Classifier: Topic :: Scientific/Engineering :: Physics
Classifier: Topic :: Scientific/Engineering :: Visualization
Requires-Python: >=3.6
License-File: LICENSE
Requires-Dist: numpy
Requires-Dist: matplotlib
Requires-Dist: astropy
Requires-Dist: scipy
Requires-Dist: setuptools
Requires-Dist: pyyaml
Requires-Dist: tqdm
